dspinlock/__init__.py
dspinlock/base.py
dspinlock/consts.py
dspinlock/exceptions.py
dspinlock/hash_dspinlock.py
dspinlock/py.typed
dspinlock/utils.py
tests/__init__.py
tests/conftest.py
tests/test_atomic_isolation.py
tests/test_mutex_state_deletion.py
py_dspinlock-0.3.1.dist-info/LICENSE
py_dspinlock-0.3.1.dist-info/METADATA
py_dspinlock-0.3.1.dist-info/WHEEL
py_dspinlock-0.3.1.dist-info/top_level.txt
py_dspinlock-0.3.1.dist-info/RECORD
