Metadata-Version: 2.1
Name: py-dspinlock
Version: 0.3.1
Summary: A distributed spinlock for Python
Home-page: https://github.com/andylamp/py-dspinlock/
Author: Andreas A. Grammenos
Author-email: ag926@cl.cam.ac.uk
License: Apache Software License 2.0
Classifier: Development Status :: 5 - Production/Stable
Classifier: Programming Language :: Python :: 3.10
Classifier: Programming Language :: Python :: 3.11
Classifier: Programming Language :: Python :: 3.12
Classifier: Programming Language :: Python :: 3.13
Classifier: License :: OSI Approved :: Apache Software License
Requires-Python: >=3.10
License-File: LICENSE
Requires-Dist: redis >=4.0.0
